appscanner/__init__.py
appscanner/__main__.py
appscanner/appscanner.py
appscanner/burst.py
appscanner/features.py
appscanner/flow.py
appscanner/preprocessor.py
appscanner/reader.py
appscanner-1.0.2.dist-info/LICENSE
appscanner-1.0.2.dist-info/METADATA
appscanner-1.0.2.dist-info/WHEEL
appscanner-1.0.2.dist-info/top_level.txt
appscanner-1.0.2.dist-info/RECORD
