Metadata-Version: 2.1
Name: appscanner
Version: 1.0.2
Summary: AppScanner: Automatic Fingerprinting of Smartphone Apps from Encrypted Network Traffic
Home-page: https://github.com/Thijsvanede/AppScanner
Author: Thijs van Ede
Author-email: t.s.vanede@utwente.nl
License: UNKNOWN
Platform: UNKNOWN
Classifier: Programming Language :: Python :: 3
Classifier: License :: OSI Approved :: MIT License
Classifier: Operating System :: OS Independent
